setup.py
probability_dsnd/Binomialdistribution.py
probability_dsnd/Gaussiandistribution.py
probability_dsnd/Generaldistribution.py
probability_dsnd/__init__.py
probability_dsnd.egg-info/PKG-INFO
probability_dsnd.egg-info/SOURCES.txt
probability_dsnd.egg-info/dependency_links.txt
probability_dsnd.egg-info/not-zip-safe
probability_dsnd.egg-info/top_level.txt