Metadata-Version: 1.0
Name: probability-dsnd
Version: 1.0
Summary: Gaussian and Binomial Distribution
Home-page: UNKNOWN
Author: Muhammad Faheem Sharif
Author-email: mfaheemsharif96@gmail.com
License: UNKNOWN
Platform: UNKNOWN
